send_recv_json.py
send_recv_json-0.1.0a1.dist-info/licenses/LICENSE
send_recv_json-0.1.0a1.dist-info/METADATA
send_recv_json-0.1.0a1.dist-info/WHEEL
send_recv_json-0.1.0a1.dist-info/top_level.txt
send_recv_json-0.1.0a1.dist-info/RECORD
