Metadata-Version: 2.4
Name: send-recv-json
Version: 0.1.0a1
Summary: Send and receive JSONs over byte streams - sockets, pipes, files, and more - using a universal, length-prefixed binary framing scheme.
Author-email: Jifeng Wu <jifengwu2k@gmail.com>
License-Expression: MIT
Project-URL: Homepage, https://github.com/jifengwu2k/send-recv-json
Project-URL: Bug Tracker, https://github.com/jifengwu2k/send-recv-json/issues
Classifier: Programming Language :: Python :: 2
Classifier: Programming Language :: Python :: 3
Classifier: Operating System :: OS Independent
Requires-Python: >=2
License-File: LICENSE
Requires-Dist: typing; python_version < "3.5"
Dynamic: license-file
